gww_service/__init__.py
gww_service/bootstrap.py
gww_service/config.py
gww_service/database.py
gww_service/earthengine.py
gww_service/main.py
gww_service/crud/__init__.py
gww_service/crud/reservoir.py
gww_service/crud/variable.py
gww_service/models/__init__.py
gww_service/models/reservoir.py
gww_service/models/time_series.py
gww_service/models/variable.py
gww_service/routers/__init__.py
gww_service/routers/images.py
gww_service/routers/reservoirs.py
gww_service/routers/time_series.py
gww_service/schemas/__init__.py
gww_service/schemas/geometry_types.py
gww_service/schemas/images.py
gww_service/schemas/reservoir.py
gww_service/schemas/time_series.py
gww_service/schemas/variable.py
gww_service-0.2.0.dist-info/LICENSE
gww_service-0.2.0.dist-info/WHEEL
gww_service-0.2.0.dist-info/METADATA
gww_service-0.2.0.dist-info/RECORD
