Metadata-Version: 2.1
Name: gww_service
Version: 0.2.0
Summary: Backend API for synchronous operations within Global Water Watch
Author-email: Jaap Langemeijer <jaaplangemeijer@gmail.com>
Requires-Python: >=3.8
Classifier: Development Status :: 3 - Alpha
Classifier: Intended Audience :: Developers
Classifier: Intended Audience :: Science/Research
Classifier: Topic :: Scientific/Engineering :: GIS
Classifier: License :: OSI Approved :: MIT License
Classifier: Programming Language :: Python :: 3
Requires-Dist: earthengine-api>=0.1.284
Requires-Dist: eepackages>=0.21
Requires-Dist: GeoAlchemy2>=0.12
Requires-Dist: geojson>=2.5
Requires-Dist: geojson-pydantic>=0.4.3
Requires-Dist: python-dateutil
Requires-Dist: shapely>=1.8
Requires-Dist: SQLAlchemy>=1.4
Requires-Dist: black ; extra == "test"
Requires-Dist: fastapi>=0.83 ; extra == "test"
Requires-Dist: httpx>=0.23 ; extra == "test"
Requires-Dist: pytest>=2.7.3 ; extra == "test"
Requires-Dist: pytest-cov ; extra == "test"
Requires-Dist: uvicorn>=0.18 ; extra == "test"
Project-URL: Source, https://github.com/global-water-watch/gww-service
Provides-Extra: test
